japy/__init__.py
japy/function_return_value.py
japy/japy_file_scanner.py
japy/japy_function.py
japy/japy_function_wrapper.py
japy/japy_server.py
japy_java_python_adapter-1.0.dist-info/LICENSE
japy_java_python_adapter-1.0.dist-info/METADATA
japy_java_python_adapter-1.0.dist-info/WHEEL
japy_java_python_adapter-1.0.dist-info/RECORD
