Metadata-Version: 2.1
Name: japy-java-python-adapter
Version: 1.0
Summary: 
Author: jasb
Author-email: jason@becker-freelance.com
Requires-Python: >=3.11,<4.0
Classifier: Programming Language :: Python :: 3
Classifier: Programming Language :: Python :: 3.11
Classifier: Programming Language :: Python :: 3.12
Classifier: Programming Language :: Python :: 3.13
Requires-Dist: aiohttp (>=3.10.10,<4.0.0)
Requires-Dist: coverage (>=7.6.2,<8.0.0)
